lyylog.py
lyylog-1.0.0.dist-info/METADATA
lyylog-1.0.0.dist-info/metadata.json
lyylog-1.0.0.dist-info/RECORD
lyylog-1.0.0.dist-info/top_level.txt
lyylog-1.0.0.dist-info/WHEEL
